pyspotlib/__init__.py
pyspotlib/client.py
pyspotlib/connection.py
pyspotlib/packetconn.py
pyspotlib/proto.py
pyspotlib/resolver.py
pyspotlib/store.py
pyspotlib-0.1.0.dist-info/METADATA
pyspotlib-0.1.0.dist-info/WHEEL
pyspotlib-0.1.0.dist-info/top_level.txt
pyspotlib-0.1.0.dist-info/RECORD
