Metadata-Version: 2.4
Name: pyspotlib
Version: 0.1.0
Summary: Python client library for Spot messaging protocol
Author-email: Mark Karpeles <magicaltux@gmail.com>
License: MIT
Project-URL: Homepage, https://github.com/KarpelesLab/pyspotlib
Project-URL: Repository, https://github.com/KarpelesLab/pyspotlib
Classifier: Development Status :: 3 - Alpha
Classifier: Intended Audience :: Developers
Classifier: License :: OSI Approved :: MIT License
Classifier: Programming Language :: Python :: 3
Classifier: Programming Language :: Python :: 3.10
Classifier: Programming Language :: Python :: 3.11
Classifier: Programming Language :: Python :: 3.12
Requires-Python: >=3.10
Requires-Dist: pybottle>=0.1.1
Requires-Dist: websockets>=12.0
Requires-Dist: cbor2>=5.6.0
Requires-Dist: httpx>=0.27.0
Provides-Extra: dev
Requires-Dist: pytest>=8.0.0; extra == "dev"
Requires-Dist: pytest-asyncio>=0.23.0; extra == "dev"
